nbchat/__init__.py
nbchat/__version__.py
nbchat/cli.py
nbchat-0.1.0.dist-info/METADATA
nbchat-0.1.0.dist-info/WHEEL
nbchat-0.1.0.dist-info/entry_points.txt
nbchat-0.1.0.dist-info/top_level.txt
nbchat-0.1.0.dist-info/RECORD
